flask_saml2/__init__.py
flask_saml2/codex.py
flask_saml2/exceptions.py
flask_saml2/signing.py
flask_saml2/types.py
flask_saml2/utils.py
flask_saml2/version.py
flask_saml2/xml_parser.py
flask_saml2/xml_templates.py
flask_saml2/idp/__init__.py
flask_saml2/idp/blueprint.py
flask_saml2/idp/idp.py
flask_saml2/idp/parser.py
flask_saml2/idp/sphandler.py
flask_saml2/idp/views.py
flask_saml2/idp/xml_render.py
flask_saml2/idp/xml_templates.py
flask_saml2/idp/ext/__init__.py
flask_saml2/idp/ext/flask_login.py
flask_saml2/idp/sp/__init__.py
flask_saml2/idp/sp/demo.py
flask_saml2/idp/sp/google_apps.py
flask_saml2/idp/sp/salesforce.py
flask_saml2/idp/templates/flask_saml2_idp/base.html
flask_saml2/idp/templates/flask_saml2_idp/invalid_user.html
flask_saml2/idp/templates/flask_saml2_idp/logged_out.html
flask_saml2/idp/templates/flask_saml2_idp/login.html
flask_saml2/idp/templates/flask_saml2_idp/metadata.xml
flask_saml2/sp/__init__.py
flask_saml2/sp/blueprint.py
flask_saml2/sp/idphandler.py
flask_saml2/sp/parser.py
flask_saml2/sp/sp.py
flask_saml2/sp/views.py
flask_saml2/sp/xml_templates.py
flask_saml2/sp/templates/flask_saml2_sp/base.html
flask_saml2/sp/templates/flask_saml2_sp/choose_idp.html
flask_saml2/sp/templates/flask_saml2_sp/metadata.xml
flask_saml2-0.0.1.dev1.dist-info/METADATA
flask_saml2-0.0.1.dev1.dist-info/RECORD
flask_saml2-0.0.1.dev1.dist-info/WHEEL
flask_saml2-0.0.1.dev1.dist-info/top_level.txt
