Metadata-Version: 2.1
Name: flask-saml2
Version: 0.0.1.dev1
Summary: SAML 2.0 IdP and SP for Flask and Python 3
Home-page: http://github.com/timheap/flask-saml2
Author: Tim Heap
Author-email: tim.heap@tidetech.org
License: MIT
Platform: UNKNOWN
Classifier: Development Status :: 3 - Alpha
Classifier: Environment :: Web Environment
Classifier: Framework :: Flask
Classifier: License :: OSI Approved :: MIT License
Classifier: Programming Language :: Python :: 3
Classifier: Programming Language :: Python :: 3.6
Classifier: Programming Language :: Python :: 3 :: Only
Classifier: Topic :: Security
Classifier: Topic :: System :: Systems Administration :: Authentication/Directory
Requires-Dist: Flask (>=1.0.0)
Requires-Dist: attrs (>=18.1.0)
Requires-Dist: defusedxml (>=0.5.0)
Requires-Dist: lxml (>=3.8.0)
Requires-Dist: pyopenssl (<18)
Requires-Dist: signxml (>=2.4.0)
